packageFarooq/__init__.py
packageFarooq-0.2.dist-info/METADATA
packageFarooq-0.2.dist-info/WHEEL
packageFarooq-0.2.dist-info/licence.txt
packageFarooq-0.2.dist-info/top_level.txt
packageFarooq-0.2.dist-info/RECORD
