Metadata-Version: 2.1
Name: packageFarooq
Version: 0.2
Summary: This is Farooq package
Author: Farooq
License-File: licence.txt
